{"airport_code":"02CD","type":"small_airport","name":"Shannon Field","continent":"NA","country_code":"US","iso_region":"US-MS","region":"MS"}
{"airport_code":"0GE5","type":"small_airport","name":"Mountain Airpark","continent":"NA","country_code":"US","iso_region":"US-GA","region":"GA"}
{"airport_code":"0MO5","type":"small_airport","name":"Joe D Lewis Airport","continent":"NA","country_code":"US","iso_region":"US-MO","region":"MO"}
{"airport_code":"0TX0","type":"small_airport","name":"Nassau Bay Airport","continent":"NA","country_code":"US","iso_region":"US-TX","region":"TX"}
{"airport_code":"15KS","type":"small_airport","name":"Sickler Airstrip","continent":"NA","country_code":"US","iso_region":"US-KS","region":"KS"}
{"airport_code":"1OH4","type":"small_airport","name":"Fortman Airport","continent":"NA","country_code":"US","iso_region":"US-OH","region":"OH"}
{"airport_code":"23CL","type":"heliport","name":"L A Co Mens Detention Cntr-Main Jail Heliport","continent":"NA","country_code":"US","iso_region":"US-CA","region":"CA"}
{"airport_code":"2FL3","type":"small_airport","name":"Folsom Airport","continent":"NA","country_code":"US","iso_region":"US-FL","region":"FL"}
{"airport_code":"2IS1","type":"heliport","name":"Proctor Hospital Heliport","continent":"NA","country_code":"US","iso_region":"US-IL","region":"IL"}
{"airport_code":"2WI2","type":"small_airport","name":"Shullsburg Airport","continent":"NA","country_code":"US","iso_region":"US-WI","region":"WI"}
{"airport_code":"31TX","type":"small_airport","name":"Scott Airport","continent":"NA","country_code":"US","iso_region":"US-TX","region":"TX"}
{"airport_code":"33CN","type":"heliport","name":"Platform Hillhouse Heliport","continent":"NA","country_code":"US","iso_region":"US-CA","region":"CA"}
{"airport_code":"33CO","type":"small_airport","name":"Melby Ranch Airstrip","continent":"NA","country_code":"US","iso_region":"US-CO","region":"CO"}
{"airport_code":"36CN","type":"small_airport","name":"Blackwell Land Company Inc Airport","continent":"NA","country_code":"US","iso_region":"US-CA","region":"CA"}
{"airport_code":"36IS","type":"small_airport","name":"Gillen Airport","continent":"NA","country_code":"US","iso_region":"US-IL","region":"IL"}
{"airport_code":"3NA6","type":"small_airport","name":"Risovi Ranch Strip","continent":"NA","country_code":"US","iso_region":"US-ND","region":"ND"}
{"airport_code":"45TA","type":"heliport","name":"Spl Heliport","continent":"NA","country_code":"US","iso_region":"US-TX","region":"TX"}
{"airport_code":"4ME4","type":"seaplane_base","name":"Lovewell Pond Seaplane Base","continent":"NA","country_code":"US","iso_region":"US-ME","region":"ME"}
{"airport_code":"4NC6","type":"small_airport","name":"Cane Creek Airport","continent":"NA","country_code":"US","iso_region":"US-NC","region":"NC"}
{"airport_code":"4TS2","type":"heliport","name":"Wilshire Place Heliport","continent":"NA","country_code":"US","iso_region":"US-TX","region":"TX"}
{"airport_code":"50AZ","type":"small_airport","name":"Rocky Ridge Airport","continent":"NA","country_code":"US","iso_region":"US-AZ","region":"AZ"}
{"airport_code":"51IN","type":"small_airport","name":"Dahnke Airport","continent":"NA","country_code":"US","iso_region":"US-IN","region":"IN"}
{"airport_code":"5OH1","type":"heliport","name":"Samaritan Hospital Heliport","continent":"NA","country_code":"US","iso_region":"US-OH","region":"OH"}
{"airport_code":"5WI0","type":"closed","name":"Grandpa's Farm Airport","continent":"NA","country_code":"US","iso_region":"US-WI","region":"WI"}
{"airport_code":"63LA","type":"small_airport","name":"Leonards Airfield & Indust Park Airport","continent":"NA","country_code":"US","iso_region":"US-LA","region":"LA"}
{"airport_code":"65NM","type":"small_airport","name":"Curtis and Curtis Airport","continent":"NA","country_code":"US","iso_region":"US-NM","region":"NM"}
{"airport_code":"66MO","type":"small_airport","name":"Ahlers Acres Airport","continent":"NA","country_code":"US","iso_region":"US-MO","region":"MO"}
{"airport_code":"6K9","type":"small_airport","name":"Keosauqua Municipal Airport","continent":"NA","country_code":"US","iso_region":"US-IA","region":"IA"}
{"airport_code":"6MD6","type":"heliport","name":"UM Charles Regional Medical Center Heliport","continent":"NA","country_code":"US","iso_region":"US-MD","region":"MD"}
{"airport_code":"6MS2","type":"small_airport","name":"Wells Farm Airport","continent":"NA","country_code":"US","iso_region":"US-MS","region":"MS"}
{"airport_code":"75AR","type":"small_airport","name":"The Bluffs Airport","continent":"NA","country_code":"US","iso_region":"US-AR","region":"AR"}
{"airport_code":"78MI","type":"small_airport","name":"Carls Airport","continent":"NA","country_code":"US","iso_region":"US-MI","region":"MI"}
{"airport_code":"78NC","type":"small_airport","name":"Fuquay/Angier Field","continent":"NA","country_code":"US","iso_region":"US-NC","region":"NC"}
{"airport_code":"7MN6","type":"small_airport","name":"Johnson Airport","continent":"NA","country_code":"US","iso_region":"US-MN","region":"MN"}
{"airport_code":"81OR","type":"small_airport","name":"Wagontire Airport","continent":"NA","country_code":"US","iso_region":"US-OR","region":"OR"}
{"airport_code":"83AK","type":"small_airport","name":"Tolovana Hot Springs Airport","continent":"NA","country_code":"US","iso_region":"US-AK","region":"AK"}
{"airport_code":"83NC","type":"heliport","name":"Holly Green Heliport","continent":"NA","country_code":"US","iso_region":"US-NC","region":"NC"}
{"airport_code":"84CA","type":"heliport","name":"Beverly Center Heliport","continent":"NA","country_code":"US","iso_region":"US-CA","region":"CA"}
{"airport_code":"84TA","type":"heliport","name":"Allied Northborough Heliport","continent":"NA","country_code":"US","iso_region":"US-TX","region":"TX"}
{"airport_code":"8AK0","type":"closed","name":"Diamond NN Cannery Airport","continent":"NA","country_code":"US","iso_region":"US-AK","region":"AK"}
{"airport_code":"8FA0","type":"seaplane_base","name":"Lake Gibson Seaplane Base","continent":"NA","country_code":"US","iso_region":"US-FL","region":"FL"}
{"airport_code":"93OH","type":"small_airport","name":"Gay Airport","continent":"NA","country_code":"US","iso_region":"US-OH","region":"OH"}
{"airport_code":"9FL5","type":"small_airport","name":"Shady Bend Airport","continent":"NA","country_code":"US","iso_region":"US-FL","region":"FL"}
{"airport_code":"9TN9","type":"small_airport","name":"Toy Box Airport","continent":"NA","country_code":"US","iso_region":"US-TN","region":"TN"}
{"airport_code":"A77","type":"small_airport","name":"Yankee Creek 2 Airport","continent":"NA","country_code":"US","iso_region":"US-AK","region":"AK"}
{"airport_code":"AGGV","type":"small_airport","name":"Suavanao Airport","continent":"OC","country_code":"SB","iso_region":"SB-IS","region":"IS"}
{"airport_code":"AL43","type":"small_airport","name":"Henley Ranch Airport","continent":"NA","country_code":"US","iso_region":"US-AL","region":"AL"}
{"airport_code":"AL80","type":"heliport","name":"Bellefonte Nuclear Plant Heliport","continent":"NA","country_code":"US","iso_region":"US-AL","region":"AL"}
{"airport_code":"AR-0093","type":"heliport","name":"Centro Cívico Grand Bourg Heliport","continent":"SA","country_code":"AR","iso_region":"AR-A","region":"A"}
{"airport_code":"AR-0297","type":"heliport","name":"Planta Cruz Del Sur Heliport","continent":"SA","country_code":"AR","iso_region":"AR-V","region":"V"}
{"airport_code":"AR-0558","type":"small_airport","name":"Santagiulian Airport","continent":"SA","country_code":"AR","iso_region":"AR-B","region":"B"}
{"airport_code":"AYCH","type":"medium_airport","name":"Chimbu Airport","continent":"OC","country_code":"PG","iso_region":"PG-CPK","region":"CPK"}
{"airport_code":"AYTD","type":"small_airport","name":"Teredau Airport","continent":"OC","country_code":"PG","iso_region":"PG-GPK","region":"GPK"}
{"airport_code":"BG-0015","type":"small_airport","name":"Trastenik Airport","continent":"EU","country_code":"BG","iso_region":"BG-18","region":"18"}
{"airport_code":"BPF","type":"small_airport","name":"Batuna Aerodrome","continent":"OC","country_code":"SB","iso_region":"SB-WE","region":"WE"}
{"airport_code":"BR-0252","type":"small_airport","name":"Fazenda Fusão Airport","continent":"SA","country_code":"BR","iso_region":"BR-AM","region":"AM"}
{"airport_code":"BR-0320","type":"heliport","name":"Quick Fazenda Cachoeira Heliport","continent":"SA","country_code":"BR","iso_region":"BR-MG","region":"MG"}
{"airport_code":"BW-0022","type":"small_airport","name":"Big Game Airport","continent":"AF","country_code":"BW","iso_region":"BW-KG","region":"KG"}
{"airport_code":"CA-0530","type":"seaplane_base","name":"Hallowell Mills Cove Seaplane Base","continent":"NA","country_code":"CA","iso_region":"CA-ON","region":"ON"}
{"airport_code":"CA-0562","type":"small_airport","name":"White Cloud Island","continent":"NA","country_code":"CA","iso_region":"CA-ON","region":"ON"}
{"airport_code":"CA-0572","type":"small_airport","name":"Goderich Municipal Airport","continent":"NA","country_code":"CA","iso_region":"CA-U-A","region":"U"}
{"airport_code":"CBK4","type":"heliport","name":"Vancouver (General Hospital) Heliport","continent":"NA","country_code":"CA","iso_region":"CA-BC","region":"BC"}
{"airport_code":"CBP2","type":"heliport","name":"Banff (Park Compound Heliport) Heliport","continent":"NA","country_code":"CA","iso_region":"CA-AB","region":"AB"}
{"airport_code":"CD21","type":"heliport","name":"Badger Mountain Heliport","continent":"NA","country_code":"US","iso_region":"US-CO","region":"CO"}
{"airport_code":"CD26","type":"heliport","name":"Peyton Heliport","continent":"NA","country_code":"US","iso_region":"US-CO","region":"CO"}
{"airport_code":"CDK2","type":"small_airport","name":"Diavik Airport","continent":"NA","country_code":"CA","iso_region":"CA-NT","region":"NT"}
{"airport_code":"CF-0005","type":"small_airport","name":"Obo Airport","continent":"AF","country_code":"CF","iso_region":"CF-HM","region":"HM"}
{"airport_code":"CGR4","type":"heliport","name":"The Ridge Heliport","continent":"NA","country_code":"CA","iso_region":"CA-BC","region":"BC"}
{"airport_code":"CHQ2","type":"closed","name":"Chicoutimi (Hydro-Québec) Heliport","continent":"NA","country_code":"CA","iso_region":"CA-QC","region":"QC"}
{"airport_code":"CKD6","type":"seaplane_base","name":"Thompson Seaplane Base","continent":"NA","country_code":"CA","iso_region":"CA-MB","region":"MB"}
{"airport_code":"CN-0003","type":"medium_airport","name":"Laohutun Air Base","continent":"AS","country_code":"CN","iso_region":"CN-21","region":"21"}
{"airport_code":"CPY2","type":"heliport","name":"Milton (District Hospital) Heliport","continent":"NA","country_code":"CA","iso_region":"CA-ON","region":"ON"}
{"airport_code":"CT85","type":"small_airport","name":"Roberts Farm Airport","continent":"NA","country_code":"US","iso_region":"US-CT","region":"CT"}
{"airport_code":"CT92","type":"heliport","name":"Bemer Heliport","continent":"NA","country_code":"US","iso_region":"US-CT","region":"CT"}
{"airport_code":"CWB2","type":"small_airport","name":"Bracebridge West Airfield","continent":"NA","country_code":"CA","iso_region":"CA-ON","region":"ON"}
{"airport_code":"CYCH","type":"medium_airport","name":"Miramichi Airport","continent":"NA","country_code":"CA","iso_region":"CA-NB","region":"NB"}
{"airport_code":"CYFB","type":"medium_airport","name":"Iqaluit Airport","continent":"NA","country_code":"CA","iso_region":"CA-NU","region":"NU"}
{"airport_code":"CYRI","type":"medium_airport","name":"Rivière-du-Loup Airport","continent":"NA","country_code":"CA","iso_region":"CA-QC","region":"QC"}
{"airport_code":"CYWH","type":"seaplane_base","name":"Victoria Harbour Seaplane Base","continent":"NA","country_code":"CA","iso_region":"CA-BC","region":"BC"}
{"airport_code":"CYXL","type":"medium_airport","name":"Sioux Lookout Airport","continent":"NA","country_code":"CA","iso_region":"CA-ON","region":"ON"}
{"airport_code":"CYYY","type":"medium_airport","name":"Mont Joli Airport","continent":"NA","country_code":"CA","iso_region":"CA-QC","region":"QC"}
{"airport_code":"CZ-0053","type":"small_airport","name":"Bynovec","continent":"EU","country_code":"CZ","iso_region":"CZ-US","region":"US"}
{"airport_code":"CZ-0082","type":"small_airport","name":"Borovník","continent":"EU","country_code":"CZ","iso_region":"CZ-JM","region":"JM"}
{"airport_code":"DE-0039","type":"small_airport","name":"Aichach Airport","continent":"EU","country_code":"DE","iso_region":"DE-BY","region":"BY"}
{"airport_code":"DE-0136","type":"small_airport","name":"Aßlarer Hütte Airfield","continent":"EU","country_code":"DE","iso_region":"DE-HE","region":"HE"}
{"airport_code":"EDEB","type":"small_airport","name":"Bad Langensalza Airport","continent":"EU","country_code":"DE","iso_region":"DE-TH","region":"TH"}
{"airport_code":"EDRX","type":"small_airport","name":"Neunkirchen-Bexbach Airport","continent":"EU","country_code":"DE","iso_region":"DE-SL","region":"SL"}
{"airport_code":"EGCE","type":"closed","name":"RAF Wrexham","continent":"EU","country_code":"GB","iso_region":"GB-WLS","region":"WLS"}
{"airport_code":"EGMK","type":"closed","name":"Lympne Airport","continent":"EU","country_code":"GB","iso_region":"GB-ENG","region":"ENG"}
{"airport_code":"EGXA","type":"closed","name":"RAF Manby","continent":"EU","country_code":"GB","iso_region":"GB-ENG","region":"ENG"}
{"airport_code":"ENVH","type":"heliport","name":"Valhall A Platform","continent":"EU","country_code":"NO","iso_region":"NO-U-A","region":"U"}
{"airport_code":"ES-0110","type":"small_airport","name":"Aeródromo de Córdoba-Villarrubia","continent":"EU","country_code":"ES","iso_region":"ES-AN","region":"AN"}
{"airport_code":"ES-0159","type":"small_airport","name":"Campo de Vuelo Moixent-Mogente","continent":"EU","country_code":"ES","iso_region":"ES-V","region":"V"}
{"airport_code":"ES-0182","type":"small_airport","name":"Aeródromo de Jaen - Las Infantas","continent":"EU","country_code":"ES","iso_region":"ES-AN","region":"AN"}
{"airport_code":"ES-0236","type":"heliport","name":"Roses Aerial Military Radar Helipad","continent":"EU","country_code":"ES","iso_region":"ES-CT","region":"CT"}
{"airport_code":"ESUA","type":"closed","name":"Åmsele Air Base","continent":"EU","country_code":"SE","iso_region":"SE-AC","region":"AC"}
{"airport_code":"F57","type":"seaplane_base","name":"Jack Browns Seaplane Base","continent":"NA","country_code":"US","iso_region":"US-FL","region":"FL"}
{"airport_code":"FA95","type":"heliport","name":"Advent Health Lake Mary ER Heliport","continent":"NA","country_code":"US","iso_region":"US-FL","region":"FL"}
{"airport_code":"FAIO","type":"closed","name":"Odi Airport","continent":"AF","country_code":"ZA","iso_region":"ZA-NW","region":"NW"}
{"airport_code":"FANA","type":"small_airport","name":"Nongoma Airport","continent":"AF","country_code":"ZA","iso_region":"ZA-NL","region":"NL"}
{"airport_code":"FBTN","type":"small_airport","name":"Tonunga Airport","continent":"AF","country_code":"BW","iso_region":"BW-CE","region":"CE"}
{"airport_code":"FCBT","type":"small_airport","name":"Loutete Airport","continent":"AF","country_code":"CG","iso_region":"CG-11","region":"11"}
{"airport_code":"FD01","type":"closed","name":"Hidden Acres Airpark","continent":"NA","country_code":"US","iso_region":"US-FL","region":"FL"}
{"airport_code":"FMNW","type":"medium_airport","name":"Ambalabe Airport","continent":"AF","country_code":"MG","iso_region":"MG-M","region":"M"}
{"airport_code":"FR-0296","type":"small_airport","name":"Mont Llaret Pic d'Aude Airfield","continent":"EU","country_code":"FR","iso_region":"FR-K","region":"K"}
{"airport_code":"FR-0347","type":"small_airport","name":"Base ULM de Mellac","continent":"EU","country_code":"FR","iso_region":"FR-E","region":"E"}
{"airport_code":"FR-0348","type":"small_airport","name":"La Motte du Caire Glider Field","continent":"EU","country_code":"FR","iso_region":"FR-U","region":"U"}
{"airport_code":"FSSB","type":"small_airport","name":"Bird Island Airport","continent":"AF","country_code":"SC","iso_region":"SC-15","region":"15"}
{"airport_code":"FYON","type":"small_airport","name":"Okahandja Airstrip","continent":"AF","country_code":"NA","iso_region":"NA-OD","region":"OD"}
{"airport_code":"FZOK","type":"small_airport","name":"Kasongo Airport","continent":"AF","country_code":"CD","iso_region":"CD-MA","region":"MA"}
{"airport_code":"GA11","type":"heliport","name":"Childrens Health Care Atl At Scottish Rite Heliport","continent":"NA","country_code":"US","iso_region":"US-GA","region":"GA"}
{"airport_code":"GB-0265","type":"small_airport","name":"Lower Withial Fram Airstrip","continent":"EU","country_code":"GB","iso_region":"GB-ENG","region":"ENG"}
{"airport_code":"GB-0336","type":"small_airport","name":"Bucknall Airfield","continent":"EU","country_code":"GB","iso_region":"GB-ENG","region":"ENG"}
{"airport_code":"GB-0365","type":"small_airport","name":"Holmbeck Farm Airfield","continent":"EU","country_code":"GB","iso_region":"GB-ENG","region":"ENG"}
{"airport_code":"GB-0392","type":"small_airport","name":"South Wales Gliding Club","continent":"EU","country_code":"GB","iso_region":"GB-WLS","region":"WLS"}
{"airport_code":"GB-FOA","type":"small_airport","name":"Foula Airfield","continent":"EU","country_code":"GB","iso_region":"GB-SCT","region":"SCT"}
{"airport_code":"HN-MSF","type":"small_airport","name":"San Francisco De La Paz Airport","continent":"NA","country_code":"HN","iso_region":"HN-OL","region":"OL"}
{"airport_code":"HU-0009","type":"small_airport","name":"Kenderes Airport","continent":"EU","country_code":"HU","iso_region":"HU-JN","region":"JN"}
{"airport_code":"IA86","type":"small_airport","name":"Hedgewood Landing Airport","continent":"NA","country_code":"US","iso_region":"US-IA","region":"IA"}
{"airport_code":"ID-0075","type":"small_airport","name":"Kaure  Airstrip","continent":"AS","country_code":"ID","iso_region":"ID-PA","region":"PA"}
{"airport_code":"ID-ZGP","type":"medium_airport","name":"Bilogai-Sugapa Airport","continent":"AS","country_code":"ID","iso_region":"ID-PA","region":"PA"}
{"airport_code":"IE-0012","type":"small_airport","name":"Ballinvally Farm Airstrip","continent":"EU","country_code":"IE","iso_region":"IE-WH","region":"WH"}
{"airport_code":"IS03","type":"closed","name":"Fox Lake Seaplane Base","continent":"NA","country_code":"US","iso_region":"US-IL","region":"IL"}
{"airport_code":"IT-0091","type":"small_airport","name":"Termon Altiport","continent":"EU","country_code":"IT","iso_region":"IT-32","region":"32"}
{"airport_code":"IT-0369","type":"small_airport","name":"\"Campo di Volo \"\"Ass.Sp.Volo Leggero\"\"\"","continent":"EU","country_code":"IT","iso_region":"IT-34","region":"34"}
{"airport_code":"IT-0385","type":"small_airport","name":"Campo di Volo Rains","continent":"EU","country_code":"IT","iso_region":"IT-72","region":"72"}
{"airport_code":"JO-0009","type":"small_airport","name":"Highway H Highway Strip","continent":"AS","country_code":"JO","iso_region":"JO-AM","region":"AM"}
{"airport_code":"JP-0069","type":"heliport","name":"Kushiro Rosai Hospital Helipad","continent":"AS","country_code":"JP","iso_region":"JP-01","region":"01"}
{"airport_code":"JP-0082","type":"heliport","name":"Ajicho Helipad","continent":"AS","country_code":"JP","iso_region":"JP-37","region":"37"}
{"airport_code":"K0M2","type":"small_airport","name":"Reelfoot Lake Airport","continent":"NA","country_code":"US","iso_region":"US-TN","region":"TN"}
{"airport_code":"K2J3","type":"small_airport","name":"Louisville Municipal Airport","continent":"NA","country_code":"US","iso_region":"US-GA","region":"GA"}
{"airport_code":"K3GV","type":"small_airport","name":"East Kansas City Airport","continent":"NA","country_code":"US","iso_region":"US-MO","region":"MO"}
{"airport_code":"K5A4","type":"small_airport","name":"Okolona Municipal-Richard Stovall Field","continent":"NA","country_code":"US","iso_region":"US-MS","region":"MS"}
{"airport_code":"K8G1","type":"small_airport","name":"Willard Airport","continent":"NA","country_code":"US","iso_region":"US-OH","region":"OH"}
{"airport_code":"KBEA","type":"small_airport","name":"Beeville Municipal Airport","continent":"NA","country_code":"US","iso_region":"US-TX","region":"TX"}
{"airport_code":"KC09","type":"small_airport","name":"Morris Municipal James R. Washburn field","continent":"NA","country_code":"US","iso_region":"US-IL","region":"IL"}
{"airport_code":"KCKA","type":"small_airport","name":"Kegelman AF Aux Field","continent":"NA","country_code":"US","iso_region":"US-OK","region":"OK"}
{"airport_code":"KDUC","type":"small_airport","name":"Halliburton Field","continent":"NA","country_code":"US","iso_region":"US-OK","region":"OK"}
{"airport_code":"KE-0100","type":"small_airport","name":"Bogani Airport","continent":"AF","country_code":"KE","iso_region":"KE-700","region":"700"}
{"airport_code":"KE-0175","type":"small_airport","name":"National Park Airstrip","continent":"AF","country_code":"KE","iso_region":"KE-200","region":"200"}
{"airport_code":"KF46","type":"small_airport","name":"Rockwall Municipal Airport","continent":"NA","country_code":"US","iso_region":"US-TX","region":"TX"}
{"airport_code":"KFIT","type":"small_airport","name":"Fitchburg Municipal Airport","continent":"NA","country_code":"US","iso_region":"US-MA","region":"MA"}
{"airport_code":"KFWA","type":"large_airport","name":"Fort Wayne International Airport","continent":"NA","country_code":"US","iso_region":"US-IN","region":"IN"}
{"airport_code":"KHLG","type":"medium_airport","name":"Wheeling Ohio County Airport","continent":"NA","country_code":"US","iso_region":"US-WV","region":"WV"}
{"airport_code":"KHMT","type":"small_airport","name":"Hemet Ryan Airport","continent":"NA","country_code":"US","iso_region":"US-CA","region":"CA"}
{"airport_code":"KI39","type":"small_airport","name":"Madison Airport","continent":"NA","country_code":"US","iso_region":"US-KY","region":"KY"}
{"airport_code":"KL71","type":"small_airport","name":"California City Municipal Airport","continent":"NA","country_code":"US","iso_region":"US-CA","region":"CA"}
{"airport_code":"KLND","type":"medium_airport","name":"Hunt Field","continent":"NA","country_code":"US","iso_region":"US-WY","region":"WY"}
{"airport_code":"KLYH","type":"medium_airport","name":"Lynchburg Regional Preston Glenn Field","continent":"NA","country_code":"US","iso_region":"US-VA","region":"VA"}
{"airport_code":"KMIC","type":"small_airport","name":"Crystal Airport","continent":"NA","country_code":"US","iso_region":"US-MN","region":"MN"}
{"airport_code":"KP52","type":"small_airport","name":"Cottonwood Airport","continent":"NA","country_code":"US","iso_region":"US-AZ","region":"AZ"}
{"airport_code":"KPTN","type":"small_airport","name":"Harry P Williams Memorial Airport","continent":"NA","country_code":"US","iso_region":"US-LA","region":"LA"}
{"airport_code":"KR-0034","type":"heliport","name":"ROK Army 102nd Armor Brigade Heliport","continent":"AS","country_code":"KR","iso_region":"KR-42","region":"42"}
{"airport_code":"KR-0067","type":"heliport","name":"C-520 Heliport","continent":"AS","country_code":"KR","iso_region":"KR-44","region":"44"}
{"airport_code":"KR-0566","type":"heliport","name":"Guksa-ro Heliport","continent":"AS","country_code":"KR","iso_region":"KR-41","region":"41"}
{"airport_code":"KR-0695","type":"heliport","name":"Wolgye (2)i-dong Heliport","continent":"AS","country_code":"KR","iso_region":"KR-11","region":"11"}
{"airport_code":"KR-0738","type":"heliport","name":"Somerset Palace Seoul Heliport","continent":"AS","country_code":"KR","iso_region":"KR-11","region":"11"}
{"airport_code":"KR-0884","type":"heliport","name":"Hyundai Hyperion Tower 1 Apartments Heliports","continent":"AS","country_code":"KR","iso_region":"KR-11","region":"11"}
{"airport_code":"KR-0962","type":"heliport","name":"Samsung Tower Palace Apartments 2 Heliports","continent":"AS","country_code":"KR","iso_region":"KR-11","region":"11"}
{"airport_code":"KR-1025","type":"heliport","name":"Grand InterContintental Seoul Parnas Heliport","continent":"AS","country_code":"KR","iso_region":"KR-11","region":"11"}
{"airport_code":"KT36","type":"small_airport","name":"Paul Pittman Memorial Airport","continent":"NA","country_code":"US","iso_region":"US-MS","region":"MS"}
{"airport_code":"KT51","type":"small_airport","name":"Dan Jones International Airport","continent":"NA","country_code":"US","iso_region":"US-TX","region":"TX"}
{"airport_code":"KU05","type":"small_airport","name":"Riddick Field","continent":"NA","country_code":"US","iso_region":"US-MT","region":"MT"}
{"airport_code":"KW-0001","type":"heliport","name":"Patton Army Heliport","continent":"AS","country_code":"KW","iso_region":"KW-AH","region":"AH"}
{"airport_code":"LECI","type":"small_airport","name":"Santa Cilia De Jaca Airport","continent":"EU","country_code":"ES","iso_region":"ES-AR","region":"AR"}
{"airport_code":"LEGE","type":"medium_airport","name":"Girona Airport","continent":"EU","country_code":"ES","iso_region":"ES-GE","region":"GE"}
{"airport_code":"LIET","type":"medium_airport","name":"Tortolì Airport","continent":"EU","country_code":"IT","iso_region":"IT-88","region":"88"}
{"airport_code":"LIMS","type":"medium_airport","name":"Piacenza San Damiano Air Base","continent":"EU","country_code":"IT","iso_region":"IT-45","region":"45"}
{"airport_code":"LL20","type":"closed","name":"Smith Restricted Landing Area","continent":"NA","country_code":"US","iso_region":"US-IL","region":"IL"}
{"airport_code":"LPCB","type":"medium_airport","name":"Aerodromo de Castelo Branco","continent":"EU","country_code":"PT","iso_region":"PT-05","region":"05"}
{"airport_code":"LS75","type":"heliport","name":"Cameron Shore Base Heliport","continent":"NA","country_code":"US","iso_region":"US-LA","region":"LA"}
{"airport_code":"LSHI","type":"heliport","name":"Inselspital Hospital Heliport","continent":"EU","country_code":"CH","iso_region":"CH-BE","region":"BE"}
{"airport_code":"LSPK","type":"closed","name":"Flugplatz Hasenstrick","continent":"EU","country_code":"CH","iso_region":"CH-ZH","region":"ZH"}
{"airport_code":"LT-0012","type":"small_airport","name":"Tukuma Novads Airstrip","continent":"EU","country_code":"LT","iso_region":"LT-U-A","region":"U"}
{"airport_code":"LTAW","type":"medium_airport","name":"Tokat Airport","continent":"AS","country_code":"TR","iso_region":"TR-60","region":"60"}
{"airport_code":"LV-0016","type":"small_airport","name":"Matīšu lidlauks","continent":"EU","country_code":"LV","iso_region":"LV-U-A","region":"U"}
{"airport_code":"MD46","type":"small_airport","name":"Glenair Airport","continent":"NA","country_code":"US","iso_region":"US-MD","region":"MD"}
{"airport_code":"MM82","type":"small_airport","name":"Laguna Del Rey Airport","continent":"NA","country_code":"MX","iso_region":"MX-COA","region":"COA"}
{"airport_code":"MNNG","type":"small_airport","name":"Nueva Guinea Airport","continent":"NA","country_code":"NI","iso_region":"NI-AS","region":"AS"}
{"airport_code":"MS15","type":"small_airport","name":"Country Club Airport","continent":"NA","country_code":"US","iso_region":"US-MS","region":"MS"}
{"airport_code":"MU89","type":"small_airport","name":"Woodland Airstrip","continent":"NA","country_code":"US","iso_region":"US-MO","region":"MO"}
{"airport_code":"MX-0015","type":"small_airport","name":"Bahía Asunción Airstrip","continent":"NA","country_code":"MX","iso_region":"MX-BCS","region":"BCS"}
{"airport_code":"MX-0867","type":"small_airport","name":"Cedros Airport","continent":"NA","country_code":"MX","iso_region":"MX-SIN","region":"SIN"}
{"airport_code":"MX-0874","type":"small_airport","name":"Nacori Chico Airport","continent":"NA","country_code":"MX","iso_region":"MX-SON","region":"SON"}
{"airport_code":"MX-0954","type":"small_airport","name":"Mesa de Los Huicholes Airstrip","continent":"NA","country_code":"MX","iso_region":"MX-NAY","region":"NAY"}
{"airport_code":"NC34","type":"small_airport","name":"Miles Airport","continent":"NA","country_code":"US","iso_region":"US-NC","region":"NC"}
{"airport_code":"NH53","type":"heliport","name":"Norden Systems Heliport","continent":"NA","country_code":"US","iso_region":"US-NH","region":"NH"}
{"airport_code":"NH78","type":"small_airport","name":"Steck Farm Airport","continent":"NA","country_code":"US","iso_region":"US-NH","region":"NH"}
{"airport_code":"NK49","type":"heliport","name":"Ibm Owego Heliport","continent":"NA","country_code":"US","iso_region":"US-NY","region":"NY"}
{"airport_code":"NL-0051","type":"heliport","name":"HeliAir","continent":"EU","country_code":"NL","iso_region":"NL-GE","region":"GE"}
{"airport_code":"NM56","type":"small_airport","name":"Mystic Bluffs Airport","continent":"NA","country_code":"US","iso_region":"US-NM","region":"NM"}
{"airport_code":"NZ-0020","type":"small_airport","name":"Center Island Airstrip","continent":"OC","country_code":"NZ","iso_region":"NZ-STL","region":"STL"}
{"airport_code":"NZJB","type":"heliport","name":"Wairau Hospital Heliport","continent":"OC","country_code":"NZ","iso_region":"NZ-MBH","region":"MBH"}
{"airport_code":"O19","type":"small_airport","name":"Kneeland Airport","continent":"NA","country_code":"US","iso_region":"US-CA","region":"CA"}
{"airport_code":"OH46","type":"heliport","name":"Adena Regional Medical Center Heliport","continent":"NA","country_code":"US","iso_region":"US-OH","region":"OH"}
{"airport_code":"OH52","type":"heliport","name":"Columbus Heliport","continent":"NA","country_code":"US","iso_region":"US-OH","region":"OH"}
{"airport_code":"OI45","type":"small_airport","name":"Shootz Field","continent":"NA","country_code":"US","iso_region":"US-OH","region":"OH"}
{"airport_code":"OR71","type":"heliport","name":"Columbia Aviation Heliport","continent":"NA","country_code":"US","iso_region":"US-OR","region":"OR"}
{"airport_code":"OR90","type":"small_airport","name":"Lafayette Airstrip","continent":"NA","country_code":"US","iso_region":"US-OR","region":"OR"}
{"airport_code":"PACE","type":"small_airport","name":"Central Airport","continent":"NA","country_code":"US","iso_region":"US-AK","region":"AK"}
{"airport_code":"PG-0042","type":"small_airport","name":"Gubil Airstrip","continent":"OC","country_code":"PG","iso_region":"PG-SAN","region":"SAN"}
{"airport_code":"PH-0074","type":"small_airport","name":"Lal-lo Airstrip","continent":"AS","country_code":"PH","iso_region":"PH-CAG","region":"CAG"}
{"airport_code":"PH-0145","type":"heliport","name":"SM Makati Heliport","continent":"AS","country_code":"PH","iso_region":"PH-U-A","region":"U"}
{"airport_code":"PMP","type":"small_airport","name":"Pimaga Airport","continent":"OC","country_code":"PG","iso_region":"PG-SHM","region":"SHM"}
{"airport_code":"RK16","type":"small_airport","name":"G 312 Airport","continent":"AS","country_code":"KR","iso_region":"KR-42","region":"42"}
{"airport_code":"RK2G","type":"heliport","name":"C 188 Heliport","continent":"AS","country_code":"KR","iso_region":"KR-41","region":"41"}
{"airport_code":"RK4J","type":"heliport","name":"C 518 Heliport","continent":"AS","country_code":"KR","iso_region":"KR-41","region":"41"}
{"airport_code":"RK8X","type":"heliport","name":"N 309 Helipad","continent":"AS","country_code":"KR","iso_region":"KR-46","region":"46"}
{"airport_code":"RU-0026","type":"small_airport","name":"Novaya Airport","continent":"AS","country_code":"RU","iso_region":"RU-SAK","region":"SAK"}
{"airport_code":"RU-0193","type":"heliport","name":"Pushkino Heliport","continent":"EU","country_code":"RU","iso_region":"RU-MOS","region":"MOS"}
{"airport_code":"RU-0226","type":"small_airport","name":"Korobcheyevo Airfield","continent":"EU","country_code":"RU","iso_region":"RU-MOS","region":"MOS"}
{"airport_code":"RU-0385","type":"small_airport","name":"Volsk Airfield","continent":"EU","country_code":"RU","iso_region":"RU-SAR","region":"SAR"}
{"airport_code":"RU-0393","type":"small_airport","name":"Krasny Yar Airport","continent":"EU","country_code":"RU","iso_region":"RU-SAM","region":"SAM"}
{"airport_code":"RU-3106","type":"closed","name":"Tiksi North Air Base","continent":"AS","country_code":"RU","iso_region":"RU-SA","region":"SA"}
{"airport_code":"RU-8226","type":"closed","name":"Vetrovoye Air Base","continent":"EU","country_code":"RU","iso_region":"RU-SAK","region":"SAK"}
{"airport_code":"S28","type":"small_airport","name":"International Peace Garden Airport","continent":"NA","country_code":"US","iso_region":"US-ND","region":"ND"}
{"airport_code":"SBIZ","type":"medium_airport","name":"Prefeito Renato Moreira Airport","continent":"SA","country_code":"BR","iso_region":"BR-MA","region":"MA"}
{"airport_code":"SCBO","type":"small_airport","name":"General Bernardo O'Higgins Base Skyway","continent":"AN","country_code":"AQ","iso_region":"AQ-U-A","region":"U"}
{"airport_code":"SCHE","type":"small_airport","name":"Rucamanqui Airport","continent":"SA","country_code":"CL","iso_region":"CL-BI","region":"BI"}
{"airport_code":"SCSJ","type":"small_airport","name":"San Javier Airport","continent":"SA","country_code":"CL","iso_region":"CL-ML","region":"ML"}
{"airport_code":"SCVL","type":"small_airport","name":"Las Marías Airport","continent":"SA","country_code":"CL","iso_region":"CL-LR","region":"LR"}
{"airport_code":"SDEA","type":"heliport","name":"Edifício HSBC Tower Heliport","continent":"SA","country_code":"BR","iso_region":"BR-SP","region":"SP"}
{"airport_code":"SDKE","type":"small_airport","name":"Coribe Airport","continent":"SA","country_code":"BR","iso_region":"BR-BA","region":"BA"}
{"airport_code":"SDKX","type":"small_airport","name":"Fazenda Agrovás Airport","continent":"SA","country_code":"BR","iso_region":"BR-MT","region":"MT"}
{"airport_code":"SDMG","type":"small_airport","name":"Haxiu Airport","continent":"SA","country_code":"BR","iso_region":"BR-RR","region":"RR"}
{"airport_code":"SDRD","type":"small_airport","name":"Adhemar Ribeiro Airport","continent":"SA","country_code":"BR","iso_region":"BR-SP","region":"SP"}
{"airport_code":"SDXD","type":"heliport","name":"IBM Tutóia Heliport","continent":"SA","country_code":"BR","iso_region":"BR-SP","region":"SP"}
{"airport_code":"SIBW","type":"small_airport","name":"Conceição Airport","continent":"SA","country_code":"BR","iso_region":"BR-PB","region":"PB"}
{"airport_code":"SIFS","type":"heliport","name":"Iguassu II Heliport","continent":"SA","country_code":"BR","iso_region":"BR-PR","region":"PR"}
{"airport_code":"SIGX","type":"small_airport","name":"Fazenda Gairova Airport","continent":"SA","country_code":"BR","iso_region":"BR-MT","region":"MT"}
{"airport_code":"SIHQ","type":"heliport","name":"Águas Claras Heliport","continent":"SA","country_code":"BR","iso_region":"BR-DF","region":"DF"}
{"airport_code":"SIQA","type":"small_airport","name":"Senador Antônio Farias Airport","continent":"SA","country_code":"BR","iso_region":"BR-RN","region":"RN"}
{"airport_code":"SIRR","type":"small_airport","name":"Lagoa dos Coqueiros Airport","continent":"SA","country_code":"BR","iso_region":"BR-MT","region":"MT"}
{"airport_code":"SJFI","type":"small_airport","name":"CIFI Airport","continent":"SA","country_code":"BR","iso_region":"BR-MT","region":"MT"}
{"airport_code":"SJGH","type":"small_airport","name":"Aeropel Airport","continent":"SA","country_code":"BR","iso_region":"BR-RS","region":"RS"}
{"airport_code":"SJHK","type":"small_airport","name":"Música Airport","continent":"SA","country_code":"BR","iso_region":"BR-RS","region":"RS"}
{"airport_code":"SJJF","type":"small_airport","name":"Pousada do Rio Roosevelt Airport","continent":"SA","country_code":"BR","iso_region":"BR-AM","region":"AM"}
{"airport_code":"SK-025","type":"small_airport","name":"Vigía Del Fuerte Airport","continent":"SA","country_code":"CO","iso_region":"CO-ANT","region":"ANT"}
{"airport_code":"SK-353","type":"small_airport","name":"Umbría Airport","continent":"SA","country_code":"CO","iso_region":"CO-MET","region":"MET"}
{"airport_code":"SLBT","type":"small_airport","name":"Buen Retiro Ballivian Airport","continent":"SA","country_code":"BO","iso_region":"BO-B","region":"B"}
{"airport_code":"SLSP","type":"small_airport","name":"Sipuati Airport","continent":"SA","country_code":"BO","iso_region":"BO-T","region":"T"}
{"airport_code":"SN52","type":"small_airport","name":"Pilot Pointe Estates Airport","continent":"NA","country_code":"US","iso_region":"US-KS","region":"KS"}
{"airport_code":"SNEG","type":"small_airport","name":"Fazenda Netolândia Airport","continent":"SA","country_code":"BR","iso_region":"BR-MT","region":"MT"}
{"airport_code":"SNIX","type":"small_airport","name":"Fazenda Masutti Airport","continent":"SA","country_code":"BR","iso_region":"BR-MT","region":"MT"}
{"airport_code":"SNNE","type":"small_airport","name":"São João Nepomuceno Airport","continent":"SA","country_code":"BR","iso_region":"BR-MG","region":"MG"}
{"airport_code":"SNUC","type":"small_airport","name":"Açu Airport","continent":"SA","country_code":"BR","iso_region":"BR-RN","region":"RN"}
{"airport_code":"SNWM","type":"small_airport","name":"Fazenda Bonito Airport","continent":"SA","country_code":"BR","iso_region":"BR-SP","region":"SP"}
{"airport_code":"SNYK","type":"heliport","name":"Cumbuco Heliport","continent":"SA","country_code":"BR","iso_region":"BR-CE","region":"CE"}
{"airport_code":"SPCC","type":"small_airport","name":"Ciudad Constitución Airport","continent":"SA","country_code":"PE","iso_region":"PE-PAS","region":"PAS"}
{"airport_code":"SSJB","type":"small_airport","name":"Salenco Airport","continent":"SA","country_code":"BR","iso_region":"BR-MS","region":"MS"}
{"airport_code":"SVCL","type":"medium_airport","name":"Calabozo Airport","continent":"SA","country_code":"VE","iso_region":"VE-J","region":"J"}
{"airport_code":"SWBN","type":"small_airport","name":"Fazenda Barreirinhos Airport","continent":"SA","country_code":"BR","iso_region":"BR-MT","region":"MT"}
{"airport_code":"SWKA","type":"small_airport","name":"Fazenda Canadá Airport","continent":"SA","country_code":"BR","iso_region":"BR-GO","region":"GO"}
{"airport_code":"SWXR","type":"small_airport","name":"Faria Airport","continent":"SA","country_code":"BR","iso_region":"BR-MT","region":"MT"}
{"airport_code":"SZP","type":"small_airport","name":"Santa Paula Airport","continent":"NA","country_code":"US","iso_region":"US-CA","region":"CA"}
{"airport_code":"TE29","type":"small_airport","name":"La Esperanza Ranch Airport","continent":"NA","country_code":"US","iso_region":"US-TX","region":"TX"}
{"airport_code":"TE43","type":"heliport","name":"Parkland Health & Hospital System Heliport","continent":"NA","country_code":"US","iso_region":"US-TX","region":"TX"}
{"airport_code":"TS74","type":"small_airport","name":"Glass Airport","continent":"NA","country_code":"US","iso_region":"US-TX","region":"TX"}
{"airport_code":"TX73","type":"closed","name":"Big Brown Creek Airstrip","continent":"NA","country_code":"US","iso_region":"US-TX","region":"TX"}
{"airport_code":"TZ-0142","type":"small_airport","name":"Sumbazi Airport","continent":"AF","country_code":"TZ","iso_region":"TZ-16","region":"16"}
{"airport_code":"U88","type":"small_airport","name":"Garden Valley Airport","continent":"NA","country_code":"US","iso_region":"US-ID","region":"ID"}
{"airport_code":"US-0097","type":"closed","name":"Tremonton Municipal Airport","continent":"NA","country_code":"US","iso_region":"US-UT","region":"UT"}
{"airport_code":"US-0148","type":"small_airport","name":"Carroll Lake-View Airport","continent":"NA","country_code":"US","iso_region":"US-TX","region":"TX"}
{"airport_code":"US-0475","type":"heliport","name":"International Falls Customs & Border Patrol Heliport","continent":"NA","country_code":"US","iso_region":"US-MN","region":"MN"}
{"airport_code":"US-0663","type":"seaplane_base","name":"Hurley Memorial Seaport","continent":"NA","country_code":"US","iso_region":"US-MN","region":"MN"}
{"airport_code":"UT84","type":"heliport","name":"Skaggs Heliport","continent":"NA","country_code":"US","iso_region":"US-UT","region":"UT"}
{"airport_code":"UUMD","type":"small_airport","name":"Selnikovo Airfield","continent":"EU","country_code":"RU","iso_region":"RU-MOS","region":"MOS"}
{"airport_code":"UZ-0016","type":"small_airport","name":"Guzar Airport","continent":"AS","country_code":"UZ","iso_region":"UZ-QA","region":"QA"}
{"airport_code":"VE-0001","type":"small_airport","name":"Acañana Airport","continent":"SA","country_code":"VE","iso_region":"VE-Z","region":"Z"}
{"airport_code":"VISP","type":"small_airport","name":"Sarsawa Air Force Station","continent":"AS","country_code":"IN","iso_region":"IN-UP","region":"UP"}
{"airport_code":"VT46","type":"small_airport","name":"Northern Lights Airport","continent":"NA","country_code":"US","iso_region":"US-VT","region":"VT"}
{"airport_code":"W29","type":"small_airport","name":"Bay Bridge Airport","continent":"NA","country_code":"US","iso_region":"US-MD","region":"MD"}
{"airport_code":"WA45","type":"small_airport","name":"Olympic Field","continent":"NA","country_code":"US","iso_region":"US-WA","region":"WA"}
{"airport_code":"WA63","type":"small_airport","name":"Pleasant Farm Airport","continent":"NA","country_code":"US","iso_region":"US-WA","region":"WA"}
{"airport_code":"WAN","type":"small_airport","name":"Waverney Airport","continent":"OC","country_code":"AU","iso_region":"AU-QLD","region":"QLD"}
{"airport_code":"WS70","type":"heliport","name":"Beaver Dam Community Hospital Heliport","continent":"NA","country_code":"US","iso_region":"US-WI","region":"WI"}
{"airport_code":"WY59","type":"small_airport","name":"Two Bar Ranch Airport","continent":"NA","country_code":"US","iso_region":"US-WY","region":"WY"}
{"airport_code":"WY61","type":"small_airport","name":"Gas Hills Airstrip","continent":"NA","country_code":"US","iso_region":"US-WY","region":"WY"}
{"airport_code":"WY64","type":"small_airport","name":"Lone Pine Flying Ranch Airport","continent":"NA","country_code":"US","iso_region":"US-WY","region":"WY"}
{"airport_code":"XS44","type":"small_airport","name":"Rancho Del Cielo Airport","continent":"NA","country_code":"US","iso_region":"US-TX","region":"TX"}
{"airport_code":"YDVE","type":"small_airport","name":"Dale River Airport","continent":"OC","country_code":"AU","iso_region":"AU-WA","region":"WA"}
{"airport_code":"YFSK","type":"small_airport","name":"Fiskville Airport","continent":"OC","country_code":"AU","iso_region":"AU-VIC","region":"VIC"}
{"airport_code":"YGIF","type":"small_airport","name":"Gifford Creek Station Airport","continent":"OC","country_code":"AU","iso_region":"AU-WA","region":"WA"}
{"airport_code":"YWHA","type":"medium_airport","name":"Whyalla Airport","continent":"OC","country_code":"AU","iso_region":"AU-SA","region":"SA"}
{"airport_code":"YWON","type":"small_airport","name":"Wonthaggi Airport","continent":"OC","country_code":"AU","iso_region":"AU-VIC","region":"VIC"}
{"airport_code":"ZA-0159","type":"small_airport","name":"FACN","continent":"AF","country_code":"ZA","iso_region":"ZA-WC","region":"WC"}
{"airport_code":"ZLXH","type":"medium_airport","name":"Gannan Xiahe Airport","continent":"AS","country_code":"CN","iso_region":"CN-62","region":"62"}
